HISTORY.rst
MANIFEST.in
README.rst
letsencrypt_remote.py
setup.py
tox.ini
letsencrypt_remote.egg-info/PKG-INFO
letsencrypt_remote.egg-info/SOURCES.txt
letsencrypt_remote.egg-info/dependency_links.txt
letsencrypt_remote.egg-info/entry_points.txt
letsencrypt_remote.egg-info/requires.txt
letsencrypt_remote.egg-info/top_level.txt