Metadata-Version: 1.1
Name: letsencrypt-remote
Version: 0.7.0
Summary: Opinionated letsencrypt acme client working via a ssh port forward.
Home-page: https://github.com/fschulze/certsling
Author: UNKNOWN
Author-email: UNKNOWN
License: UNKNOWN
Platform: UNKNOWN
Classifier: Development Status :: 4 - Beta
Classifier: Intended Audience :: System Administrators
Classifier: License :: OSI Approved :: MIT License
Classifier: Programming Language :: Python
Classifier: Programming Language :: Python :: 3.4
